{
  "bomFormat": "CycloneDX",
  "specVersion": "1.5",
  "serialNumber": "urn:uuid:83bddacf-3a96-4654-9f35-fa6f675e8b8c",
  "version": 1,
  "metadata": {
    "timestamp": "2023-11-14T17:53:55.089Z",
    "tools": {
      "components": [
        {
          "group": "@cyclonedx",
          "name": "cdxgen",
          "version": "9.9.3",
          "purl": "pkg:npm/%40cyclonedx/cdxgen@9.9.3",
          "type": "application",
          "bom-ref": "pkg:npm/@cyclonedx/cdxgen@9.9.3",
          "author": "OWASP Foundation",
          "publisher": "OWASP Foundation"
        }
      ]
    },
    "authors": [
      {
        "name": "OWASP Foundation"
      }
    ]
  },
  "components": [],
  "services": [],
  "dependencies": []
}
