{
  "bomFormat": "CycloneDX",
  "specVersion": "1.5",
  "serialNumber": "urn:uuid:08ad49f7-b9c3-491a-8f60-b8e9290d88fd",
  "version": 1,
  "metadata": {
    "timestamp": "2023-11-14T18:04:56.839Z",
    "tools": {
      "components": [
        {
          "group": "@cyclonedx",
          "name": "cdxgen",
          "version": "9.9.3",
          "purl": "pkg:npm/%40cyclonedx/cdxgen@9.9.3",
          "type": "application",
          "bom-ref": "pkg:npm/@cyclonedx/cdxgen@9.9.3",
          "author": "OWASP Foundation",
          "publisher": "OWASP Foundation"
        }
      ]
    },
    "authors": [
      {
        "name": "OWASP Foundation"
      }
    ]
  },
  "components": [],
  "services": [],
  "dependencies": []
}
