{
  "bomFormat": "CycloneDX",
  "specVersion": "1.5",
  "serialNumber": "urn:uuid:3b69696a-f8a3-482f-9d44-d4976c669e36",
  "version": 1,
  "metadata": {
    "timestamp": "2023-11-14T19:12:09.105Z",
    "tools": {
      "components": [
        {
          "group": "@cyclonedx",
          "name": "cdxgen",
          "version": "9.9.3",
          "purl": "pkg:npm/%40cyclonedx/cdxgen@9.9.3",
          "type": "application",
          "bom-ref": "pkg:npm/@cyclonedx/cdxgen@9.9.3",
          "author": "OWASP Foundation",
          "publisher": "OWASP Foundation"
        }
      ]
    },
    "authors": [
      {
        "name": "OWASP Foundation"
      }
    ]
  },
  "components": [],
  "services": [],
  "dependencies": []
}
