{
  "bomFormat": "CycloneDX",
  "specVersion": "1.5",
  "serialNumber": "urn:uuid:f245e9ec-0992-4fc6-8692-bce277e3dc7b",
  "version": 1,
  "metadata": {
    "timestamp": "2023-11-14T19:24:26.831Z",
    "tools": {
      "components": [
        {
          "group": "@cyclonedx",
          "name": "cdxgen",
          "version": "9.9.3",
          "purl": "pkg:npm/%40cyclonedx/cdxgen@9.9.3",
          "type": "application",
          "bom-ref": "pkg:npm/@cyclonedx/cdxgen@9.9.3",
          "author": "OWASP Foundation",
          "publisher": "OWASP Foundation"
        }
      ]
    },
    "authors": [
      {
        "name": "OWASP Foundation"
      }
    ]
  },
  "components": [],
  "services": [],
  "dependencies": []
}
